adaptive_neighbourhoods/__init__.py
adaptive_neighbourhoods/_types.py
adaptive_neighbourhoods/distances.py
adaptive_neighbourhoods/neighbourhoods.py
adaptive_neighbourhoods-0.0.2.dist-info/METADATA
adaptive_neighbourhoods-0.0.2.dist-info/WHEEL
adaptive_neighbourhoods-0.0.2.dist-info/licenses/LICENSE
adaptive_neighbourhoods-0.0.2.dist-info/RECORD
