Metadata-Version: 2.1
Name: adaptive_neighbourhoods
Version: 0.0.2
Summary: Python API for generating adapted and unique neighbourhoods for searching for adversarial examples.
Project-URL: Homepage, https://github.com/jaypmorgan/adaptive-neighbourhoods
Project-URL: Bug Tracker, https://github.com/jaypmorgan/adaptive-neighbourhoods/issues
Author: Adeline Paiement, Arno Pauly, Monika Seisenberger
Author-email: Jay Morgan <jaymiles17@gmail.com>
License-File: LICENSE
Classifier: License :: OSI Approved :: GNU General Public License v3 (GPLv3)
Classifier: Operating System :: OS Independent
Classifier: Programming Language :: Python :: 3
Requires-Python: >=3.6
